wagtail_sharing-2.15.dist-info/licenses/LICENSE
wagtailsharing/__init__.py
wagtailsharing/apps.py
wagtailsharing/helpers.py
wagtailsharing/models.py
wagtailsharing/urls.py
wagtailsharing/views.py
wagtailsharing/wagtail_hooks.py
wagtailsharing/migrations/0001_initial.py
wagtailsharing/migrations/0002_shareableroutablepage.py
wagtailsharing/migrations/0003_delete_shareableroutablepage.py
wagtailsharing/migrations/0004_bigautofield.py
wagtailsharing/migrations/__init__.py
wagtailsharing/routers/__init__.py
wagtailsharing/routers/base.py
wagtailsharing/routers/db.py
wagtailsharing/routers/settings.py
wagtailsharing/templates/wagtailsharing/banner.html
wagtailsharing/tests/__init__.py
wagtailsharing/tests/helpers.py
wagtailsharing/tests/settings.py
wagtailsharing/tests/test_helpers.py
wagtailsharing/tests/test_models.py
wagtailsharing/tests/test_urls.py
wagtailsharing/tests/test_views.py
wagtailsharing/tests/test_wagtail_hooks.py
wagtailsharing/tests/urls.py
wagtailsharing/tests/routers/__init__.py
wagtailsharing/tests/routers/test_base.py
wagtailsharing/tests/routers/test_db.py
wagtailsharing/tests/routers/test_routers.py
wagtailsharing/tests/routers/test_settings.py
wagtailsharing/tests/shareable_routable_testapp/__init__.py
wagtailsharing/tests/shareable_routable_testapp/apps.py
wagtailsharing/tests/shareable_routable_testapp/models.py
wagtailsharing/tests/shareable_routable_testapp/migrations/0001_initial.py
wagtailsharing/tests/shareable_routable_testapp/migrations/0002_testpage.py
wagtailsharing/tests/shareable_routable_testapp/migrations/__init__.py
wagtail_sharing-2.15.dist-info/METADATA
wagtail_sharing-2.15.dist-info/WHEEL
wagtail_sharing-2.15.dist-info/top_level.txt
wagtail_sharing-2.15.dist-info/RECORD
